lusid_configuration/__init__.py
lusid_configuration/__version__.py
lusid_configuration/api_client.py
lusid_configuration/configuration.py
lusid_configuration/exceptions.py
lusid_configuration/rest.py
lusid_configuration/api/__init__.py
lusid_configuration/api/application_metadata_api.py
lusid_configuration/api/configuration_sets_api.py
lusid_configuration/models/__init__.py
lusid_configuration/models/access_controlled_action.py
lusid_configuration/models/access_controlled_resource.py
lusid_configuration/models/action_id.py
lusid_configuration/models/configuration_item.py
lusid_configuration/models/configuration_item_summary.py
lusid_configuration/models/configuration_set.py
lusid_configuration/models/configuration_set_summary.py
lusid_configuration/models/create_configuration_item.py
lusid_configuration/models/create_configuration_set.py
lusid_configuration/models/id_selector_definition.py
lusid_configuration/models/identifier_part_schema.py
lusid_configuration/models/link.py
lusid_configuration/models/lusid_problem_details.py
lusid_configuration/models/lusid_validation_problem_details.py
lusid_configuration/models/personal_access_token.py
lusid_configuration/models/resource_id.py
lusid_configuration/models/resource_list_of_access_controlled_resource.py
lusid_configuration/models/resource_list_of_configuration_item.py
lusid_configuration/models/resource_list_of_configuration_set.py
lusid_configuration/models/resource_list_of_configuration_set_summary.py
lusid_configuration/models/update_configuration_item.py
lusid_configuration/models/update_configuration_set.py
lusid_configuration/utilities/__init__.py
lusid_configuration/utilities/config_keys.json
lusid_configuration/utilities/config_keys.py
lusid_configuration_sdk_preview-0.1.559.dist-info/METADATA
lusid_configuration_sdk_preview-0.1.559.dist-info/WHEEL
lusid_configuration_sdk_preview-0.1.559.dist-info/top_level.txt
lusid_configuration_sdk_preview-0.1.559.dist-info/RECORD
